ipfabric_logicmonitor/__init__.py
ipfabric_logicmonitor/ipf.py
ipfabric_logicmonitor/lm.py
ipfabric_logicmonitor/matching.py
ipfabric_logicmonitor/models/__init__.py
ipfabric_logicmonitor/models/ipf_models.py
ipfabric_logicmonitor/models/lm_models.py
ipfabric_logicmonitor/models/merged_models.py
ipfabric_logicmonitor/tools/__init__.py
ipfabric_logicmonitor/tools/lm.py
ipfabric_logicmonitor/tools/shared.py
ipfabric_logicmonitor-0.1.0b3.dist-info/LICENSE
ipfabric_logicmonitor-0.1.0b3.dist-info/METADATA
ipfabric_logicmonitor-0.1.0b3.dist-info/WHEEL
ipfabric_logicmonitor-0.1.0b3.dist-info/RECORD
