Metadata-Version: 2.1
Name: ipfabric_logicmonitor
Version: 0.1.0b3
Summary: Package supporting IP Fabric LogicMonitor Integration
Home-page: https://gitlab.com/ip-fabric/integrations/ipfabric_logicmonitor
License: MIT
Keywords: ipfabric,ip-fabric,community-fabric
Author: Justin Jeffery
Author-email: justin.jeffery@ipfabric.io
Requires-Python: >=3.8.1,<4.0.0
Classifier: License :: OSI Approved :: MIT License
Classifier: Programming Language :: Python :: 3
Classifier: Programming Language :: Python :: 3.9
Classifier: Programming Language :: Python :: 3.10
Classifier: Programming Language :: Python :: 3.11
Classifier: Programming Language :: Python :: 3.12
Requires-Dist: ipfabric (>=6.6.0b4,<7.0.0)
Requires-Dist: logicmonitor-sdk (>=3.0.200,<4.0.0)
Requires-Dist: typing-extensions (>=4.7.1,<5.0.0)
Project-URL: IP Fabric, https://ipfabric.io/
Project-URL: Repository, https://gitlab.com/ip-fabric/integrations/ipfabric_logicmonitor
